{"en": {"reusability": ["Training methods that combine privacy protection mechanisms with generative algorithms", "Efficient training framework design", "Model architecture suitable for high privacy protection scenarios"], "limitations": []}, "es": {"reusability": ["Métodos de entrenamiento que combinan mecanismos de protección de la privacidad con algoritmos generativos", "Diseño de un marco de entrenamiento eficiente", "Arquitectura de modelo adecuada para escenarios de alta protección de la privacidad"], "limitations": []}}